simsimd.cpython-38-x86_64-linux-gnu.so
simsimd/__init__.pyi
simsimd/py.typed
simsimd.libs/libgomp-8949ffbe.so.1.0.0
simsimd-6.5.12.dist-info/LICENSE
simsimd-6.5.12.dist-info/METADATA
simsimd-6.5.12.dist-info/WHEEL
simsimd-6.5.12.dist-info/top_level.txt
simsimd-6.5.12.dist-info/RECORD
simsimd-6.5.12.dist-info/sboms/auditwheel.cdx.json
